flask_ligand/__init__.py
flask_ligand/cli.py
flask_ligand/controllers.py
flask_ligand/default_settings.py
flask_ligand/py.typed
flask_ligand/schemas.py
flask_ligand/extensions/__init__.py
flask_ligand/extensions/api.py
flask_ligand/extensions/database.py
flask_ligand/extensions/jwt.py
flask_ligand/views/__init__.py
flask_ligand/views/openapi.py
flask_ligand/views/common/__init__.py
flask_ligand/views/common/openapi_doc.py
flask_ligand-0.8.1.data/data/README.rst/README.rst
flask_ligand-0.8.1.data/data/flask_ligand/py.typed/py.typed
flask_ligand-0.8.1.dist-info/AUTHORS
flask_ligand-0.8.1.dist-info/LICENSE
flask_ligand-0.8.1.dist-info/METADATA
flask_ligand-0.8.1.dist-info/WHEEL
flask_ligand-0.8.1.dist-info/pbr.json
flask_ligand-0.8.1.dist-info/top_level.txt
flask_ligand-0.8.1.dist-info/RECORD
