Metadata-Version: 2.1
Name: flask-ligand
Version: 0.8.1
Summary: A simple flask library for building microservices with RBAC JWT security, OpenAPI client and SQLAlchemy database support.
Author: Ryan Gard
Author-email: ryan@gardiancapitol.com
License: GNU Affero General Public License v3
Project-URL: Changelog, https://github.com/cowofevil/flask-ligand/blob/main/CHANGELOG.md
Project-URL: Source, https://github.com/cowofevil/flask-ligand
Project-URL: Tracker, https://github.com/cowofevil/flask-ligand/issues
Keywords: flask
Classifier: Development Status :: 4 - Beta
Classifier: Intended Audience :: Developers
Classifier: Framework :: Flask
Classifier: Operating System :: MacOS :: MacOS X
Classifier: Operating System :: Microsoft :: Windows
Classifier: Operating System :: POSIX
Classifier: Natural Language :: English
Classifier: Programming Language :: Python :: 3
Classifier: Programming Language :: Python :: 3 :: Only
Classifier: Programming Language :: Python :: 3.10
Classifier: Programming Language :: Python :: 3.11
Classifier: Topic :: Software Development :: Libraries
Classifier: Topic :: Software Development :: Libraries :: Application Frameworks
Classifier: Typing :: Typed
Requires-Python: >=3.10
License-File: LICENSE
License-File: AUTHORS
Requires-Dist: flask (~=2.2)
Requires-Dist: PyJWT (~=2.6)
Requires-Dist: sqlalchemy (~=1.4)
Requires-Dist: cryptography (>=36.0.2)
Requires-Dist: flask-cors (~=3.0)
Requires-Dist: Flask-Migrate (~=4.0)
Requires-Dist: Flask-JWT-Extended (~=4.4)
Requires-Dist: flask-smorest (==0.41)
Requires-Dist: flask-sqlalchemy (~=3.0)
Requires-Dist: gunicorn (~=20.1)
Requires-Dist: marshmallow-sqlalchemy (~=0.29)
Requires-Dist: python-dotenv (~=1.0)
Requires-Dist: requests (~=2.30)
Requires-Dist: sqlalchemy-utils (~=0.40)
Requires-Dist: urljoin (==1.0.0)
